web2app/__init__.py
web2app/errors.py
web2app/web2exe.py
web2app-1.0.1.dist-info/licenses/LICENSE
web2app-1.0.1.dist-info/METADATA
web2app-1.0.1.dist-info/WHEEL
web2app-1.0.1.dist-info/top_level.txt
web2app-1.0.1.dist-info/RECORD
