Metadata-Version: 2.4
Name: web2app
Version: 1.0.1
Summary: PyPI package for converting a website into an app.
Author-email: uukelele-scratch <robustrobot11@gmail.com>
License: MIT License
Project-URL: Homepage, https://github.com/uukelele-scratch/web2app
Project-URL: Repository, https://github.com/uukelele-scratch/web2app
Classifier: Programming Language :: Python :: 3
Classifier: License :: OSI Approved :: MIT License
Classifier: Operating System :: OS Independent
Requires-Python: >=3.7
License-File: LICENSE
Requires-Dist: Pillow>=11.1.0
Requires-Dist: requests>=2.32.3
Requires-Dist: beautifulsoup4>=4.12.3
Dynamic: license-file
